{
    "configurations": [
        {
            "name": "arm",
            "includePath": [
                "${workspaceFolder}/**",
                "${workspaceFolder}/src",
                "${workspaceFolder}/src/asf/sam/boards",
                "${workspaceFolder}/src/asf/sam/utils",
                "${workspaceFolder}/src/asf/sam/utils/header_files",
                "${workspaceFolder}/src/asf/sam/utils/preprocessor",
                "${workspaceFolder}/src/asf/sam/utils/cmsis/sam3x/include",
                "${workspaceFolder}/src/asf/sam/utils/cmsis/sam3x/source/templates",
                "${workspaceFolder}/src/asf/common/boards",
                "${workspaceFolder}/src/asf/common/utils",
                "${workspaceFolder}/src/asf/thirdparty/CMSIS/include",
                "${workspaceFolder}/src/asf/common/services/gpio",
                "${workspaceFolder}/src/asf/common/services/clock",
                "${workspaceFolder}/src/asf/common/services/delay",
                "${workspaceFolder}/src/asf/common/services/ioport",
                "${workspaceFolder}/src/asf/sam/drivers/pmc",
                "${workspaceFolder}/src/asf/sam/drivers/pio",
                "${workspaceFolder}/src/asf/sam/drivers/uart",
                "${workspaceFolder}/src/asf/sam/drivers/usart",
                "${workspaceFolder}/src/asf/sam/drivers/dacc",
                "${workspaceFolder}/src/asf/sam/drivers/tc",
                "${vcpkgRoot}/x64-windows/include",
                "${vcpkgRoot}/x86-windows/include"
            ],
            "defines": [
                "_DEBUG",
                "UNICODE",
                "_UNICODE",
                "ARM_MATH_CM3=true",
                "BOARD=ARDUINO_DUE_X",
                "__SAM3X8E",
                "printf=iprintf",
                "scanf=iscanf",
                "__GNUC__"
            ],
            "windowsSdkVersion": "10.0.18362.0",
            "compilerPath": "D:/Active/ProgramFiles/Atmel/Studio/7.0/toolchain/arm/arm-gnu-toolchain/bin/arm-none-eabi-gcc.exe",
            "cStandard": "c11",
            "cppStandard": "c++11",
            "intelliSenseMode": "linux-gcc-arm"
        }
    ],
    "version": 4
}